{
  "ok": true,
  "kind": "regular",
  "hours": 2,
  "source": "cli_run",
  "generated_at": "2026-06-24T01:34:51",
  "report": "📊 [주식] 최근 1시간 뉴스\n----------------\n06/24 10:31 KST | 최근 2시간 | 신규 이슈 11개\n시황 1줄: KOSDAQ -12.13% / S&P500 -2.50% / Nasdaq -4.11% / USD/KRW 1,535.6\n수급/시장: 시장 중립 이하, 뉴스 단독 추격 주의 / 투자자별 수급 확인불가\n선별방식: 매매전략 없이 뉴스 중요도·신선도·수급 배경만 표시\n\n📌 핵심 이슈\n1) [100/A] 2026.06.24 08:32:26 기업명: 한국항공우주\n  • 시각: 최신 36분 전 / 최초 1시간 57분 전 / 반복 30건\n  • 원문: https://t.me/Yeouido_Lab/34932\n  • 관련종목: 한국항공우주(047810.KS), NAVER(035420.KS)\n\n2) [100/A] SK하이닉스, '조정은 비중 확대 기회' 증권사 발표에 강세\n  • 시각: 최신 16분 전 / 최초 2시간 2분 전 / 반복 8건\n  • 원문: https://t.me/rassiro_channel/296749\n  • 관련종목: SK하이닉스(000660.KS)\n\n3) [100/A] 코스피 8,312.4P (+1.3%↑) 삼성물산, 삼성전자등 상승\n  • 시각: 최신 14분 전 / 최초 1시간 49분 전 / 반복 4건\n  • 원문: https://t.me/rassiro_channel/296733\n  • 관련종목: 삼성전자(005930.KS)\n\n4) [100/A] [리포트 브리핑]삼성전기, '1위 업체는 Premium을 받아야 마땅하다' 목표가 2,800,000원\n  • 시각: 최신 12분 전 / 최초 57분 전 / 반복 3건\n  • 원문: https://t.me/rassiro_channel/296746\n  • 관련종목: 현대차(005380.KS)\n\n5) [100/A] #CPSP 캐나다 조달청장 \"잠수함 수주전, '경제 혜택' 집중 검증\"\n  • 시각: 최신 1시간 54분 전 / 최초 1시간 56분 전 / 반복 2건\n  • 원문: https://t.me/sharpha/47392\n  • 관련종목: 직접 언급 없음\n\n6) [100/A] 조창현 사내이사, 세아메카닉스의 지분율 0.03% 확대\n  • 시각: 최신 36분 전 / 최초 1시간 56분 전 / 반복 6건\n  • 원문: https://t.me/rassiro_channel/296750\n  • 관련종목: 직접 언급 없음\n\n7) [100/A] 🚀 [KRX 상승률 TOP10] 2026-06-24 09:30 (KST)\n  • 시각: 최신 1시간 1분 전 / 반복 1건\n  • 원문: https://t.me/moneythemestock/61416\n  • 관련종목: KST(KST)\n\n8) [100/A] [리포트 브리핑]현대모비스, '짙어지는 로보틱스 사업자의 면모' 목표가 810,000원\n  • 시각: 최신 1시간 36분 전 / 반복 1건\n  • 원문: https://t.me/rassiro_channel/296729\n  • 관련종목: 현대모비스(012330.KS)\n\n9) [100/A] 엔비디아, PCB 업체에 10% 가격 인하 요구? • 최근 시장에서 ‘엔비디아가 PCB 제조업체에 가격 10% 인하 요구’, ‘…\n  • 시각: 최신 1시간 1분 전 / 반복 1건\n  • 원문: https://t.me/realtime_stock_news/60183\n  • 관련종목: 직접 언급 없음\n\n10) [100/A] >>TSMC, 첨단 공정 칩 가격 전면 인상 예정\n  • 시각: 최신 18분 전 / 최초 27분 전 / 반복 2건\n  • 원문: https://t.me/realtime_stock_news/60188\n  • 관련종목: 직접 언급 없음\n\n11) [100/A] 일본 서비스 PPI 실제 3.3% (예상치 3.3%, 이전치 3.0%) $MACRO ...\n  • 시각: 최신 1시간 39분 전 / 반복 1건\n  • 원문: https://t.me/FastStockNewsUSA/20971\n  • 관련종목: MACRO(MACRO)\n\n⚡ 관심 섹터 순위: AI인프라 > 반도체 > 방산/항공 > 로봇\n검증: 로컬인사이트엔진 · 엄격: 중요 이슈만 선별 · 원문 220건 → 신규 11개 선별 · 중복억제 0건"
}